boxkite/__init__.py
boxkite/monitoring/__init__.py
boxkite/monitoring/context.py
boxkite/monitoring/encoder.py
boxkite/monitoring/frequency.py
boxkite/monitoring/registry.py
boxkite/monitoring/service.py
boxkite/monitoring/collector/__init__.py
boxkite/monitoring/collector/baseline.py
boxkite/monitoring/collector/computed.py
boxkite/monitoring/collector/feature.py
boxkite/monitoring/collector/inference.py
boxkite/monitoring/collector/info.py
boxkite/monitoring/collector/type.py
boxkite/monitoring/exporter/__init__.py
boxkite/monitoring/exporter/fluentd_exporter.py
boxkite/monitoring/exporter/type.py
boxkite/utils/__init__.py
boxkite/utils/histogram.py
tests/__init__.py
tests/mockserver.py
tests/test_exporter.py
tests/test_frequency.py
tests/test_histogram.py
tests/test_scoring.py
tests/test_serving.py
tests/test_training.py
boxkite-0.0.5.dist-info/LICENSE
boxkite-0.0.5.dist-info/METADATA
boxkite-0.0.5.dist-info/WHEEL
boxkite-0.0.5.dist-info/top_level.txt
boxkite-0.0.5.dist-info/RECORD
