Metadata-Version: 2.1
Name: boxkite
Version: 0.0.5
Summary: A small example package
Home-page: https://github.com/basisai/boxkite
Author: Luke Marsden
Author-email: me@lukemarsden.net
License: UNKNOWN
Platform: UNKNOWN
Classifier: Programming Language :: Python :: 3
Classifier: Programming Language :: Python :: 3.6
Classifier: Programming Language :: Python :: 3.7
Classifier: Programming Language :: Python :: 3.8
Classifier: Programming Language :: Python :: 3.9
Classifier: License :: OSI Approved :: Apache Software License
Classifier: Operating System :: OS Independent
Requires-Python: >=3.6
License-File: LICENSE
Requires-Dist: fluent-logger (<0.11,>=0.10.0)
Requires-Dist: prometheus-client (<0.12,>=0.10.1)
Requires-Dist: numpy (<2,>=1.16)
Requires-Dist: dataclasses ; python_version < "3.7"
